{
  "queries": [
    {
      "section": "Character Data",
      "block_sha256": "sha256:9c58283fa17c5afebbdc471ffb1af78cbadbed662cd983380cce0866244c3212",
      "raw": "{{#cargo_query:tables=SF6_CharacterData\n|fields=CONCAT('[[file:', portrait, '|100px|link=]] ')=<big>Guile</big>,hp=HP,throwRange=Throw<br>Range,fwdWalkSpd=Fwd Walk<br>Speed,bwdWalkSpd=Back Walk<br>Speed,fwdDashSpd=Fwd Dash<br>Speed,bwdDashSpd=Back Dash<br>Speed,fwdDashDist=Fwd Dash<br>Distance,bwdDashDist=Back Dash<br>Distance,jumpSpd=Jump<br>Speed,fwdJumpDist=Fwd Jump<br>Distance,bwdJumpDist=Back Jump<br>Distance,jumpApex=Jump<br>Apex\n|where=chara=\"Guile\"\n|format=table\n|order by=_rowID\n|rows per page=50\n}}"
    },
    {
      "section": "Normals and Target Combos",
      "block_sha256": "sha256:897101f5e161c40fb2d01e48a7d7a841db39590573b6c8f386385a87a9f225e5",
      "raw": "{{#cargo_query:tables=SF6_FrameData\n|fields=input,IF(damage='{{{damage}}}', \"\", damage)=Damage,IF(startup='{{{startup}}}', \"\", startup)=Startup,IF(active='{{{active}}}', \"\", active)=Active,IF(recovery='{{{recovery}}}', \"\", recovery)=Recovery,IF(total='{{{total}}}', \"\", total)=Total,IF(hitAdv='{{{hitAdv}}}', \"\", hitAdv)=Hit Adv,IF(blockAdv='{{{blockAdv}}}', \"\", blockAdv)=Block Adv,IF(guard='{{{guard}}}', \"\", guard)=Guard,IF(cancel='{{{cancel}}}', \"\", cancel)=Cancel,IF(hitconfirm='{{{hitconfirm}}}', \"\", hitconfirm)=Hitconfirm\n|where=chara=\"Guile\"  and (moveType=\"ground_normal\" or moveType=\"normal\" or moveType=\"air_normal\")\n|format=dynamic table\n|order by=_rowID\n|rows per page=50\n}}"
    },
    {
      "section": "Normals and Target Combos",
      "block_sha256": "sha256:4e18785ed64bec52ac38053daeb7354ac43d6c471adbd4763fb49c9bfd645434",
      "raw": "{{#cargo_query:tables=SF6_FrameData\n|fields=input,IF(dmgScaling='{{{dmgScaling}}}', \"\", dmgScaling)=Dmg Scaling,IF(punishAdv='{{{punishAdv}}}', \"\", punishAdv)=Punish Adv,IF(perfParryAdv='{{{perfParryAdv}}}', \"\", perfParryAdv)=PerfParry Adv,IF(DRcancelHit='{{{DRcancelHit}}}', \"\", DRcancelHit)=DR Cancel onHit,IF(DRcancelBlk='{{{DRcancelBlk}}}', \"\", DRcancelBlk)=DR Cancel onBlock,IF(afterDRHit='{{{afterDRHit}}}', \"\", afterDRHit)=After DR onHit,IF(afterDRBlk='{{{afterDRBlk}}}', \"\", afterDRBlk)=After DR onBlock,IF(hitstun='{{{hitstun}}}', \"\", hitstun)=Hitstun,IF(blockstun='{{{blockstun}}}', \"\", blockstun)=Blockstun,IF(hitstop='{{{hitstop}}}', \"\", hitstop)=Hitstop\n|where=chara=\"Guile\"  and (moveType=\"ground_normal\" or moveType=\"normal\" or moveType=\"air_normal\")\n|format=dynamic table\n|order by=_rowID\n|rows per page=50\n}}"
    },
    {
      "section": "Normals and Target Combos",
      "block_sha256": "sha256:10b646798cc03a1c77c7cea314cbe7cf4edf046dcb681043743a8809b2944260",
      "raw": "{{#cargo_query:tables=SF6_FrameData\n|fields=input,IF(driveDmgBlk='{{{driveDmgBlk}}}', \"\", driveDmgBlk)=DriveDmg Block,IF(driveDmgHit='{{{driveDmgHit}}}', \"\", driveDmgHit)=DriveDmg Hit[PC],IF(driveGain='{{{driveGain}}}', \"\", driveGain)=Drive Gain,IF(superGainHit='{{{superGainHit}}}', \"\", superGainHit)=SuperGain Hit,IF(superGainBlk='{{{superGainBlk}}}', \"\", superGainBlk)=SuperGain Block\n|where=chara=\"Guile\"  and (moveType=\"ground_normal\" or moveType=\"normal\" or moveType=\"air_normal\")\n|format=dynamic table\n|order by=_rowID\n|rows per page=50\n}}"
    },
    {
      "section": "Normals and Target Combos",
      "block_sha256": "sha256:426a7f8e47e7c08e0835e3a38928bde9eff997c5169a41049397989d79f23780",
      "raw": "{{#cargo_query:tables=SF6_FrameData\n|fields=input,IF(invuln='{{{invuln}}}', \"\", invuln)=Invuln,IF(armor='{{{armor}}}', \"\", armor)=Armor,IF(airborne='{{{airborne}}}', \"\", airborne)=Airborne,IF(atkRange='{{{atkRange}}}', \"\", atkRange)=Range,IF(jugStart='{{{jugStart}}}', \"\", jugStart)=Juggle Start,IF(jugIncrease='{{{jugIncrease}}}', \"\", jugIncrease)=Juggle Increase,IF(jugLimit='{{{jugLimit}}}', \"\", jugLimit)=Juggle Limit\n|where=chara=\"Guile\"  and (moveType=\"ground_normal\" or moveType=\"normal\" or moveType=\"air_normal\")\n|format=dynamic table\n|order by=_rowID\n|rows per page=50\n}}"
    },
    {
      "section": "Normals and Target Combos",
      "block_sha256": "sha256:fccf25c958c81c8f854db5a1b5916d341e7541977611ef619378d257a0324e33",
      "raw": "{{#cargo_query:tables=SF6_FrameData\n|fields=input,IF(notes='{{{notes}}}', \"\", notes)=Notes\n|where=chara=\"Guile\"  and (moveType=\"ground_normal\" or moveType=\"normal\" or moveType=\"air_normal\")\n|format=dynamic table\n|order by=_rowID\n|rows per page=50\n}}"
    },
    {
      "section": "Drive and Throw",
      "block_sha256": "sha256:e7245db6a228cbbd3ef71699fd504e22e3423daa5cf1d08d511eb7046092b066",
      "raw": "{{#cargo_query:tables=SF6_FrameData\n|fields=input,IF(damage='{{{damage}}}', \"\", damage)=Damage,IF(startup='{{{startup}}}', \"\", startup)=Startup,IF(active='{{{active}}}', \"\", active)=Active,IF(recovery='{{{recovery}}}', \"\", recovery)=Recovery,IF(total='{{{total}}}', \"\", total)=Total,IF(hitAdv='{{{hitAdv}}}', \"\", hitAdv)=Hit Adv,IF(blockAdv='{{{blockAdv}}}', \"\", blockAdv)=Block Adv,IF(guard='{{{guard}}}', \"\", guard)=Guard\n|where=chara=\"Guile\"  and (moveType = \"drive\" or moveType=\"throw\")\n|format=dynamic table\n|order by=_rowID\n|rows per page=50\n}}"
    },
    {
      "section": "Drive and Throw",
      "block_sha256": "sha256:18ee8251f98ad8636763f673edb22187ef3bc1b0e51a4393eea5cfd5e1dec4a3",
      "raw": "{{#cargo_query:tables=SF6_FrameData\n|fields=input,IF(chip='{{{chip}}}', \"\", chip)=Chip,IF(dmgScaling='{{{dmgScaling}}}', \"\", dmgScaling)=Dmg Scaling,IF(punishAdv='{{{punishAdv}}}', \"\", punishAdv)=Punish Adv,IF(perfParryAdv='{{{perfParryAdv}}}', \"\", perfParryAdv)=PerfParry Adv,IF(blockstun='{{{blockstun}}}', \"\", blockstun)=Blockstun,IF(hitstop='{{{hitstop}}}', \"\", hitstop)=Hitstop\n|where=chara=\"Guile\"  and (moveType = \"drive\" or moveType=\"throw\")\n|format=dynamic table\n|order by=_rowID\n|rows per page=50\n}}"
    },
    {
      "section": "Drive and Throw",
      "block_sha256": "sha256:25cc5dcef05d90e3a7cdad8da698883621aef9115089580fe30f1275e73582e4",
      "raw": "{{#cargo_query:tables=SF6_FrameData\n|fields=input,IF(driveDmgBlk='{{{driveDmgBlk}}}', \"\", driveDmgBlk)=DriveDmg Block,IF(driveDmgHit='{{{driveDmgHit}}}', \"\", driveDmgHit)=DriveDmg Hit[PC],IF(driveGain='{{{driveGain}}}', \"\", driveGain)=Drive Gain,IF(superGainHit='{{{superGainHit}}}', \"\", superGainHit)=SuperGain Hit\n|where=chara=\"Guile\"  and (moveType = \"drive\" or moveType=\"throw\")\n|format=dynamic table\n|order by=_rowID\n|rows per page=50\n}}"
    },
    {
      "section": "Drive and Throw",
      "block_sha256": "sha256:326ff98a27cc1d06b8a11078245d7e8c220f117ef9d2cce96a53433b9dd9bf9c",
      "raw": "{{#cargo_query:tables=SF6_FrameData\n|fields=input,IF(invuln='{{{invuln}}}', \"\", invuln)=Invuln,IF(armor='{{{armor}}}', \"\", armor)=Armor,IF(atkRange='{{{atkRange}}}', \"\", atkRange)=Range,IF(jugStart='{{{jugStart}}}', \"\", jugStart)=Juggle Start,IF(jugIncrease='{{{jugIncrease}}}', \"\", jugIncrease)=Juggle Increase,IF(jugLimit='{{{jugLimit}}}', \"\", jugLimit)=Juggle Limit\n|where=chara=\"Guile\"  and (moveType = \"drive\" or moveType=\"throw\")\n|format=dynamic table\n|order by=_rowID\n|rows per page=50\n}}"
    },
    {
      "section": "Drive and Throw",
      "block_sha256": "sha256:a97b4008ff6cb05c0e9f67aaad62b7adeed852ce61c08e6fbb041f8303f844e9",
      "raw": "{{#cargo_query:tables=SF6_FrameData\n|fields=input,IF(notes='{{{notes}}}', \"\", notes)=Notes\n|where=chara=\"Guile\"  and (moveType = \"drive\" or moveType=\"throw\")\n|format=dynamic table\n|order by=_rowID\n|rows per page=50\n}}"
    },
    {
      "section": "Specials",
      "block_sha256": "sha256:9832ad3dfdfc3235dea1c2705b23b9551ab44ebecd65185718cd074c473bff1d",
      "raw": "{{#cargo_query:tables=SF6_FrameData\n|fields=input,IF(damage='{{{damage}}}', \"\", damage)=Damage,IF(startup='{{{startup}}}', \"\", startup)=Startup,IF(active='{{{active}}}', \"\", active)=Active,IF(recovery='{{{recovery}}}', \"\", recovery)=Recovery,IF(total='{{{total}}}', \"\", total)=Total,IF(hitAdv='{{{hitAdv}}}', \"\", hitAdv)=Hit Adv,IF(blockAdv='{{{blockAdv}}}', \"\", blockAdv)=Block Adv,IF(guard='{{{guard}}}', \"\", guard)=Guard,IF(cancel='{{{cancel}}}', \"\", cancel)=Cancel,IF(hitconfirm='{{{hitconfirm}}}', \"\", hitconfirm)=Hitconfirm\n|where=chara=\"Guile\"  and moveType = \"special\"\n|format=dynamic table\n|order by=_rowID\n|rows per page=50\n}}"
    },
    {
      "section": "Specials",
      "block_sha256": "sha256:29c413ddc0d2d48a4c015d865b3b1604c5069d57308939cf5c28aa914142d234",
      "raw": "{{#cargo_query:tables=SF6_FrameData\n|fields=input,IF(chip='{{{chip}}}', \"\", chip)=Chip,IF(dmgScaling='{{{dmgScaling}}}', \"\", dmgScaling)=Dmg Scaling,IF(punishAdv='{{{punishAdv}}}', \"\", punishAdv)=Punish Adv,IF(perfParryAdv='{{{perfParryAdv}}}', \"\", perfParryAdv)=PerfParry Adv,IF(blockstun='{{{blockstun}}}', \"\", blockstun)=Blockstun,IF(hitstop='{{{hitstop}}}', \"\", hitstop)=Hitstop\n|where=chara=\"Guile\"  and moveType = \"special\"\n|format=dynamic table\n|order by=_rowID\n|rows per page=50\n}}"
    },
    {
      "section": "Specials",
      "block_sha256": "sha256:d18052e6a34f6b9fb5e9712fef15ebaf133a75187bfc0fe2d021c3e0245d3763",
      "raw": "{{#cargo_query:tables=SF6_FrameData\n|fields=input,IF(driveDmgBlk='{{{driveDmgBlk}}}', \"\", driveDmgBlk)=DriveDmg Block,IF(driveDmgHit='{{{driveDmgHit}}}', \"\", driveDmgHit)=DriveDmg Hit[PC],IF(driveGain='{{{driveGain}}}', \"\", driveGain)=Drive Gain,IF(superGainHit='{{{superGainHit}}}', \"\", superGainHit)=SuperGain Hit,IF(superGainBlk='{{{superGainBlk}}}', \"\", superGainBlk)=SuperGain Block\n|where=chara=\"Guile\"  and moveType = \"special\"\n|format=dynamic table\n|order by=_rowID\n|rows per page=50\n}}"
    },
    {
      "section": "Specials",
      "block_sha256": "sha256:75f50742f119c3c79269ff289c0731f2d69b5c613f3aba6885c48497fba1616f",
      "raw": "{{#cargo_query:tables=SF6_FrameData\n|fields=input,IF(invuln='{{{invuln}}}', \"\", invuln)=Invuln,IF(armor='{{{armor}}}', \"\", armor)=Armor,IF(airborne='{{{airborne}}}', \"\", airborne)=Airborne,IF(atkRange='{{{atkRange}}}', \"\", atkRange)=Range,IF(jugStart='{{{jugStart}}}', \"\", jugStart)=Juggle Start,IF(jugIncrease='{{{jugIncrease}}}', \"\", jugIncrease)=Juggle Increase,IF(jugLimit='{{{jugLimit}}}', \"\", jugLimit)=Juggle Limit\n|where=chara=\"Guile\"  and moveType = \"special\"\n|format=dynamic table\n|order by=_rowID\n|rows per page=50\n}}"
    },
    {
      "section": "Specials",
      "block_sha256": "sha256:64f04b292789c0172f46262892625f5c1173e07fa124a73969ff4bc2bec369aa",
      "raw": "{{#cargo_query:tables=SF6_FrameData\n|fields=input,IF(notes='{{{notes}}}', \"\", notes)=Notes\n|where=chara=\"Guile\"  and moveType = \"special\"\n|format=dynamic table\n|order by=_rowID\n|rows per page=50\n}}"
    },
    {
      "section": "Supers",
      "block_sha256": "sha256:73141d6fbdaea7c1663d9003685b253c3a5f60b9870649325fef1d5c83b5a8bd",
      "raw": "{{#cargo_query:tables=SF6_FrameData\n|fields=input,IF(damage='{{{damage}}}', \"\", damage)=Damage,IF(startup='{{{startup}}}', \"\", startup)=Startup,IF(active='{{{active}}}', \"\", active)=Active,IF(recovery='{{{recovery}}}', \"\", recovery)=Recovery,IF(total='{{{total}}}', \"\", total)=Total,IF(hitAdv='{{{hitAdv}}}', \"\", hitAdv)=Hit Adv,IF(blockAdv='{{{blockAdv}}}', \"\", blockAdv)=Block Adv,IF(guard='{{{guard}}}', \"\", guard)=Guard\n|where=chara=\"Guile\"  and moveType = \"super\"\n|format=dynamic table\n|order by=_rowID\n|rows per page=50\n}}"
    },
    {
      "section": "Supers",
      "block_sha256": "sha256:6af71f7c33b5c0afc55758bf3aadd9579d869dd0809d6fa530fecd15007020fc",
      "raw": "{{#cargo_query:tables=SF6_FrameData\n|fields=input,IF(chip='{{{chip}}}', \"\", chip)=Chip,IF(dmgScaling='{{{dmgScaling}}}', \"\", dmgScaling)=Dmg Scaling,IF(punishAdv='{{{punishAdv}}}', \"\", punishAdv)=Punish Adv,IF(perfParryAdv='{{{perfParryAdv}}}', \"\", perfParryAdv)=PerfParry Adv,IF(blockstun='{{{blockstun}}}', \"\", blockstun)=Blockstun,IF(hitstop='{{{hitstop}}}', \"\", hitstop)=Hitstop\n|where=chara=\"Guile\"  and moveType = \"super\"\n|format=dynamic table\n|order by=_rowID\n|rows per page=50\n}}"
    },
    {
      "section": "Supers",
      "block_sha256": "sha256:333163e5282223beac9219cb6d72e1ea60e621d355a66be8c963c078bea270cf",
      "raw": "{{#cargo_query:tables=SF6_FrameData\n|fields=input,IF(driveDmgBlk='{{{driveDmgBlk}}}', \"\", driveDmgBlk)=DriveDmg Block,IF(driveDmgHit='{{{driveDmgHit}}}', \"\", driveDmgHit)=DriveDmg Hit[PC],IF(superGainHit='{{{superGainHit}}}', \"\", superGainHit)=SuperGain Hit,IF(superGainBlk='{{{superGainBlk}}}', \"\", superGainBlk)=SuperGain Block\n|where=chara=\"Guile\"  and moveType = \"super\"\n|format=dynamic table\n|order by=_rowID\n|rows per page=50\n}}"
    },
    {
      "section": "Supers",
      "block_sha256": "sha256:d8d53d0c8d9980f386b431bffc874aedac7c37b199843d2625c634253136e680",
      "raw": "{{#cargo_query:tables=SF6_FrameData\n|fields=input,IF(invuln='{{{invuln}}}', \"\", invuln)=Invuln,IF(armor='{{{armor}}}', \"\", armor)=Armor,IF(airborne='{{{airborne}}}', \"\", airborne)=Airborne,IF(atkRange='{{{atkRange}}}', \"\", atkRange)=Range,IF(jugStart='{{{jugStart}}}', \"\", jugStart)=Juggle Start,IF(jugIncrease='{{{jugIncrease}}}', \"\", jugIncrease)=Juggle Increase,IF(jugLimit='{{{jugLimit}}}', \"\", jugLimit)=Juggle Limit\n|where=chara=\"Guile\"  and moveType = \"super\"\n|format=dynamic table\n|order by=_rowID\n|rows per page=50\n}}"
    },
    {
      "section": "Supers",
      "block_sha256": "sha256:c59ec775a60ba460fa73077b59102c54d2f61f8dc953a7d1825af5a8b6b804ef",
      "raw": "{{#cargo_query:tables=SF6_FrameData\n|fields=input,IF(notes='{{{notes}}}', \"\", notes)=Notes\n|where=chara=\"Guile\"  and moveType = \"super\"\n|format=dynamic table\n|order by=_rowID\n|rows per page=50\n}}"
    }
  ]
}