{
  "batchcomplete": true,
  "query": {
    "pages": [
      {
        "pageid": 58425,
        "ns": 6,
        "title": "File:SF6 Battle HUD.jpg",
        "imagerepository": "local",
        "imageinfo": [
          {
            "timestamp": "2022-12-22T08:55:32Z",
            "user": "Spabobin",
            "size": 521720,
            "width": 1600,
            "height": 919,
            "comment": "",
            "url": "https://wiki.supercombo.gg/images/9/9d/SF6_Battle_HUD.jpg",
            "descriptionurl": "https://wiki.supercombo.gg/w/File:SF6_Battle_HUD.jpg",
            "descriptionshorturl": "https://wiki.supercombo.gg/index.php?curid=58425",
            "sha1": "96b9273f80026a3c6b5b669b36ca51861b6bffb7",
            "metadata": [
              {
                "name": "MEDIAWIKI_EXIF_VERSION",
                "value": 1
              }
            ],
            "commonmetadata": [],
            "extmetadata": {
              "DateTime": {
                "value": "2022-12-22T08:55:32Z",
                "source": "mediawiki-metadata",
                "hidden": ""
              },
              "ObjectName": {
                "value": "SF6 Battle HUD",
                "source": "mediawiki-metadata"
              }
            },
            "mime": "image/jpeg"
          }
        ]
      },
      {
        "pageid": 68789,
        "ns": 6,
        "title": "File:SF6 icon combocount.png",
        "imagerepository": "local",
        "imageinfo": [
          {
            "timestamp": "2023-01-19T22:30:14Z",
            "user": "Spabobin",
            "size": 18985,
            "width": 302,
            "height": 91,
            "comment": "",
            "url": "https://wiki.supercombo.gg/images/5/5f/SF6_icon_combocount.png",
            "descriptionurl": "https://wiki.supercombo.gg/w/File:SF6_icon_combocount.png",
            "descriptionshorturl": "https://wiki.supercombo.gg/index.php?curid=68789",
            "sha1": "92301ccb75c9111fd3def4f724348d131ff94551",
            "metadata": [
              {
                "name": "frameCount",
                "value": 0
              },
              {
                "name": "loopCount",
                "value": 1
              },
              {
                "name": "duration",
                "value": 0
              },
              {
                "name": "bitDepth",
                "value": 8
              },
              {
                "name": "colorType",
                "value": "truecolour-alpha"
              },
              {
                "name": "metadata",
                "value": [
                  {
                    "name": "XResolution",
                    "value": "3779/100"
                  },
                  {
                    "name": "YResolution",
                    "value": "3779/100"
                  },
                  {
                    "name": "ResolutionUnit",
                    "value": 3
                  },
                  {
                    "name": "_MW_PNG_VERSION",
                    "value": 1
                  }
                ]
              }
            ],
            "commonmetadata": [
              {
                "name": "XResolution",
                "value": "3779/100"
              },
              {
                "name": "YResolution",
                "value": "3779/100"
              },
              {
                "name": "ResolutionUnit",
                "value": 3
              }
            ],
            "extmetadata": {
              "DateTime": {
                "value": "2023-01-19T22:30:14Z",
                "source": "mediawiki-metadata",
                "hidden": ""
              },
              "ObjectName": {
                "value": "SF6 icon combocount",
                "source": "mediawiki-metadata"
              }
            },
            "mime": "image/png"
          }
        ]
      },
      {
        "pageid": 68790,
        "ns": 6,
        "title": "File:SF6 icon counterhit.png",
        "imagerepository": "local",
        "imageinfo": [
          {
            "timestamp": "2023-01-19T22:30:16Z",
            "user": "Spabobin",
            "size": 13106,
            "width": 330,
            "height": 40,
            "comment": "",
            "url": "https://wiki.supercombo.gg/images/b/be/SF6_icon_counterhit.png",
            "descriptionurl": "https://wiki.supercombo.gg/w/File:SF6_icon_counterhit.png",
            "descriptionshorturl": "https://wiki.supercombo.gg/index.php?curid=68790",
            "sha1": "aa44a8109ef479c415f6daa387b25a2a6c9ef9d2",
            "metadata": [
              {
                "name": "frameCount",
                "value": 0
              },
              {
                "name": "loopCount",
                "value": 1
              },
              {
                "name": "duration",
                "value": 0
              },
              {
                "name": "bitDepth",
                "value": 8
              },
              {
                "name": "colorType",
                "value": "truecolour-alpha"
              },
              {
                "name": "metadata",
                "value": [
                  {
                    "name": "XResolution",
                    "value": "3779/100"
                  },
                  {
                    "name": "YResolution",
                    "value": "3779/100"
                  },
                  {
                    "name": "ResolutionUnit",
                    "value": 3
                  },
                  {
                    "name": "_MW_PNG_VERSION",
                    "value": 1
                  }
                ]
              }
            ],
            "commonmetadata": [
              {
                "name": "XResolution",
                "value": "3779/100"
              },
              {
                "name": "YResolution",
                "value": "3779/100"
              },
              {
                "name": "ResolutionUnit",
                "value": 3
              }
            ],
            "extmetadata": {
              "DateTime": {
                "value": "2023-01-19T22:30:16Z",
                "source": "mediawiki-metadata",
                "hidden": ""
              },
              "ObjectName": {
                "value": "SF6 icon counterhit",
                "source": "mediawiki-metadata"
              }
            },
            "mime": "image/png"
          }
        ]
      },
      {
        "pageid": 68791,
        "ns": 6,
        "title": "File:SF6 icon crossup.png",
        "imagerepository": "local",
        "imageinfo": [
          {
            "timestamp": "2023-01-19T22:30:17Z",
            "user": "Spabobin",
            "size": 24897,
            "width": 660,
            "height": 40,
            "comment": "",
            "url": "https://wiki.supercombo.gg/images/b/b6/SF6_icon_crossup.png",
            "descriptionurl": "https://wiki.supercombo.gg/w/File:SF6_icon_crossup.png",
            "descriptionshorturl": "https://wiki.supercombo.gg/index.php?curid=68791",
            "sha1": "ee883d77c3a06006ca9b54ea362f08c05bcf3a1d",
            "metadata": [
              {
                "name": "frameCount",
                "value": 0
              },
              {
                "name": "loopCount",
                "value": 1
              },
              {
                "name": "duration",
                "value": 0
              },
              {
                "name": "bitDepth",
                "value": 8
              },
              {
                "name": "colorType",
                "value": "truecolour-alpha"
              },
              {
                "name": "metadata",
                "value": [
                  {
                    "name": "XResolution",
                    "value": "3779/100"
                  },
                  {
                    "name": "YResolution",
                    "value": "3779/100"
                  },
                  {
                    "name": "ResolutionUnit",
                    "value": 3
                  },
                  {
                    "name": "_MW_PNG_VERSION",
                    "value": 1
                  }
                ]
              }
            ],
            "commonmetadata": [
              {
                "name": "XResolution",
                "value": "3779/100"
              },
              {
                "name": "YResolution",
                "value": "3779/100"
              },
              {
                "name": "ResolutionUnit",
                "value": 3
              }
            ],
            "extmetadata": {
              "DateTime": {
                "value": "2023-01-19T22:30:17Z",
                "source": "mediawiki-metadata",
                "hidden": ""
              },
              "ObjectName": {
                "value": "SF6 icon crossup",
                "source": "mediawiki-metadata"
              }
            },
            "mime": "image/png"
          }
        ]
      },
      {
        "pageid": 68792,
        "ns": 6,
        "title": "File:SF6 icon crush.png",
        "imagerepository": "local",
        "imageinfo": [
          {
            "timestamp": "2023-01-19T22:30:19Z",
            "user": "Spabobin",
            "size": 20985,
            "width": 660,
            "height": 40,
            "comment": "",
            "url": "https://wiki.supercombo.gg/images/d/d1/SF6_icon_crush.png",
            "descriptionurl": "https://wiki.supercombo.gg/w/File:SF6_icon_crush.png",
            "descriptionshorturl": "https://wiki.supercombo.gg/index.php?curid=68792",
            "sha1": "d16a59dfffdeb628713ef4e385997ec86fc36f01",
            "metadata": [
              {
                "name": "frameCount",
                "value": 0
              },
              {
                "name": "loopCount",
                "value": 1
              },
              {
                "name": "duration",
                "value": 0
              },
              {
                "name": "bitDepth",
                "value": 8
              },
              {
                "name": "colorType",
                "value": "truecolour-alpha"
              },
              {
                "name": "metadata",
                "value": [
                  {
                    "name": "XResolution",
                    "value": "3779/100"
                  },
                  {
                    "name": "YResolution",
                    "value": "3779/100"
                  },
                  {
                    "name": "ResolutionUnit",
                    "value": 3
                  },
                  {
                    "name": "_MW_PNG_VERSION",
                    "value": 1
                  }
                ]
              }
            ],
            "commonmetadata": [
              {
                "name": "XResolution",
                "value": "3779/100"
              },
              {
                "name": "YResolution",
                "value": "3779/100"
              },
              {
                "name": "ResolutionUnit",
                "value": 3
              }
            ],
            "extmetadata": {
              "DateTime": {
                "value": "2023-01-19T22:30:19Z",
                "source": "mediawiki-metadata",
                "hidden": ""
              },
              "ObjectName": {
                "value": "SF6 icon crush",
                "source": "mediawiki-metadata"
              }
            },
            "mime": "image/png"
          }
        ]
      },
      {
        "pageid": 68793,
        "ns": 6,
        "title": "File:SF6 icon hkd.png",
        "imagerepository": "local",
        "imageinfo": [
          {
            "timestamp": "2023-01-19T22:30:20Z",
            "user": "Spabobin",
            "size": 33895,
            "width": 660,
            "height": 40,
            "comment": "",
            "url": "https://wiki.supercombo.gg/images/c/c1/SF6_icon_hkd.png",
            "descriptionurl": "https://wiki.supercombo.gg/w/File:SF6_icon_hkd.png",
            "descriptionshorturl": "https://wiki.supercombo.gg/index.php?curid=68793",
            "sha1": "413d9ff4b3e478a45a4761adf53ee948f26ea715",
            "metadata": [
              {
                "name": "frameCount",
                "value": 0
              },
              {
                "name": "loopCount",
                "value": 1
              },
              {
                "name": "duration",
                "value": 0
              },
              {
                "name": "bitDepth",
                "value": 8
              },
              {
                "name": "colorType",
                "value": "truecolour-alpha"
              },
              {
                "name": "metadata",
                "value": [
                  {
                    "name": "XResolution",
                    "value": "3779/100"
                  },
                  {
                    "name": "YResolution",
                    "value": "3779/100"
                  },
                  {
                    "name": "ResolutionUnit",
                    "value": 3
                  },
                  {
                    "name": "_MW_PNG_VERSION",
                    "value": 1
                  }
                ]
              }
            ],
            "commonmetadata": [
              {
                "name": "XResolution",
                "value": "3779/100"
              },
              {
                "name": "YResolution",
                "value": "3779/100"
              },
              {
                "name": "ResolutionUnit",
                "value": 3
              }
            ],
            "extmetadata": {
              "DateTime": {
                "value": "2023-01-19T22:30:20Z",
                "source": "mediawiki-metadata",
                "hidden": ""
              },
              "ObjectName": {
                "value": "SF6 icon hkd",
                "source": "mediawiki-metadata"
              }
            },
            "mime": "image/png"
          }
        ]
      },
      {
        "pageid": 68794,
        "ns": 6,
        "title": "File:SF6 icon punishcounter.png",
        "imagerepository": "local",
        "imageinfo": [
          {
            "timestamp": "2023-01-19T22:30:21Z",
            "user": "Spabobin",
            "size": 19535,
            "width": 330,
            "height": 50,
            "comment": "",
            "url": "https://wiki.supercombo.gg/images/9/9d/SF6_icon_punishcounter.png",
            "descriptionurl": "https://wiki.supercombo.gg/w/File:SF6_icon_punishcounter.png",
            "descriptionshorturl": "https://wiki.supercombo.gg/index.php?curid=68794",
            "sha1": "1f9d353a7ff331e4989738751a369c8f1dc9139f",
            "metadata": [
              {
                "name": "frameCount",
                "value": 0
              },
              {
                "name": "loopCount",
                "value": 1
              },
              {
                "name": "duration",
                "value": 0
              },
              {
                "name": "bitDepth",
                "value": 8
              },
              {
                "name": "colorType",
                "value": "truecolour-alpha"
              },
              {
                "name": "metadata",
                "value": [
                  {
                    "name": "XResolution",
                    "value": "3779/100"
                  },
                  {
                    "name": "YResolution",
                    "value": "3779/100"
                  },
                  {
                    "name": "ResolutionUnit",
                    "value": 3
                  },
                  {
                    "name": "_MW_PNG_VERSION",
                    "value": 1
                  }
                ]
              }
            ],
            "commonmetadata": [
              {
                "name": "XResolution",
                "value": "3779/100"
              },
              {
                "name": "YResolution",
                "value": "3779/100"
              },
              {
                "name": "ResolutionUnit",
                "value": 3
              }
            ],
            "extmetadata": {
              "DateTime": {
                "value": "2023-01-19T22:30:21Z",
                "source": "mediawiki-metadata",
                "hidden": ""
              },
              "ObjectName": {
                "value": "SF6 icon punishcounter",
                "source": "mediawiki-metadata"
              }
            },
            "mime": "image/png"
          }
        ]
      },
      {
        "pageid": 68795,
        "ns": 6,
        "title": "File:SF6 icon reversal.png",
        "imagerepository": "local",
        "imageinfo": [
          {
            "timestamp": "2023-01-19T22:30:23Z",
            "user": "Spabobin",
            "size": 23801,
            "width": 660,
            "height": 40,
            "comment": "",
            "url": "https://wiki.supercombo.gg/images/c/cd/SF6_icon_reversal.png",
            "descriptionurl": "https://wiki.supercombo.gg/w/File:SF6_icon_reversal.png",
            "descriptionshorturl": "https://wiki.supercombo.gg/index.php?curid=68795",
            "sha1": "965b5aa70076850a524f60e8fbb105d40be92926",
            "metadata": [
              {
                "name": "frameCount",
                "value": 0
              },
              {
                "name": "loopCount",
                "value": 1
              },
              {
                "name": "duration",
                "value": 0
              },
              {
                "name": "bitDepth",
                "value": 8
              },
              {
                "name": "colorType",
                "value": "truecolour-alpha"
              },
              {
                "name": "metadata",
                "value": [
                  {
                    "name": "XResolution",
                    "value": "3779/100"
                  },
                  {
                    "name": "YResolution",
                    "value": "3779/100"
                  },
                  {
                    "name": "ResolutionUnit",
                    "value": 3
                  },
                  {
                    "name": "_MW_PNG_VERSION",
                    "value": 1
                  }
                ]
              }
            ],
            "commonmetadata": [
              {
                "name": "XResolution",
                "value": "3779/100"
              },
              {
                "name": "YResolution",
                "value": "3779/100"
              },
              {
                "name": "ResolutionUnit",
                "value": 3
              }
            ],
            "extmetadata": {
              "DateTime": {
                "value": "2023-01-19T22:30:23Z",
                "source": "mediawiki-metadata",
                "hidden": ""
              },
              "ObjectName": {
                "value": "SF6 icon reversal",
                "source": "mediawiki-metadata"
              }
            },
            "mime": "image/png"
          }
        ]
      },
      {
        "pageid": 68796,
        "ns": 6,
        "title": "File:SF6 icon stun.png",
        "imagerepository": "local",
        "imageinfo": [
          {
            "timestamp": "2023-01-19T22:30:24Z",
            "user": "Spabobin",
            "size": 19032,
            "width": 660,
            "height": 40,
            "comment": "",
            "url": "https://wiki.supercombo.gg/images/0/08/SF6_icon_stun.png",
            "descriptionurl": "https://wiki.supercombo.gg/w/File:SF6_icon_stun.png",
            "descriptionshorturl": "https://wiki.supercombo.gg/index.php?curid=68796",
            "sha1": "86ba4642ec591986b4f5cf775a7649819cb5da25",
            "metadata": [
              {
                "name": "frameCount",
                "value": 0
              },
              {
                "name": "loopCount",
                "value": 1
              },
              {
                "name": "duration",
                "value": 0
              },
              {
                "name": "bitDepth",
                "value": 8
              },
              {
                "name": "colorType",
                "value": "truecolour-alpha"
              },
              {
                "name": "metadata",
                "value": [
                  {
                    "name": "XResolution",
                    "value": "3779/100"
                  },
                  {
                    "name": "YResolution",
                    "value": "3779/100"
                  },
                  {
                    "name": "ResolutionUnit",
                    "value": 3
                  },
                  {
                    "name": "_MW_PNG_VERSION",
                    "value": 1
                  }
                ]
              }
            ],
            "commonmetadata": [
              {
                "name": "XResolution",
                "value": "3779/100"
              },
              {
                "name": "YResolution",
                "value": "3779/100"
              },
              {
                "name": "ResolutionUnit",
                "value": 3
              }
            ],
            "extmetadata": {
              "DateTime": {
                "value": "2023-01-19T22:30:24Z",
                "source": "mediawiki-metadata",
                "hidden": ""
              },
              "ObjectName": {
                "value": "SF6 icon stun",
                "source": "mediawiki-metadata"
              }
            },
            "mime": "image/png"
          }
        ]
      },
      {
        "pageid": 68797,
        "ns": 6,
        "title": "File:SF6 icon throwescape.png",
        "imagerepository": "local",
        "imageinfo": [
          {
            "timestamp": "2023-01-19T22:30:24Z",
            "user": "Spabobin",
            "size": 28945,
            "width": 660,
            "height": 40,
            "comment": "",
            "url": "https://wiki.supercombo.gg/images/6/6a/SF6_icon_throwescape.png",
            "descriptionurl": "https://wiki.supercombo.gg/w/File:SF6_icon_throwescape.png",
            "descriptionshorturl": "https://wiki.supercombo.gg/index.php?curid=68797",
            "sha1": "8ac398617c6724e9593f6b8154f86beb01a6fc7e",
            "metadata": [
              {
                "name": "frameCount",
                "value": 0
              },
              {
                "name": "loopCount",
                "value": 1
              },
              {
                "name": "duration",
                "value": 0
              },
              {
                "name": "bitDepth",
                "value": 8
              },
              {
                "name": "colorType",
                "value": "truecolour-alpha"
              },
              {
                "name": "metadata",
                "value": [
                  {
                    "name": "XResolution",
                    "value": "3779/100"
                  },
                  {
                    "name": "YResolution",
                    "value": "3779/100"
                  },
                  {
                    "name": "ResolutionUnit",
                    "value": 3
                  },
                  {
                    "name": "_MW_PNG_VERSION",
                    "value": 1
                  }
                ]
              }
            ],
            "commonmetadata": [
              {
                "name": "XResolution",
                "value": "3779/100"
              },
              {
                "name": "YResolution",
                "value": "3779/100"
              },
              {
                "name": "ResolutionUnit",
                "value": 3
              }
            ],
            "extmetadata": {
              "DateTime": {
                "value": "2023-01-19T22:30:24Z",
                "source": "mediawiki-metadata",
                "hidden": ""
              },
              "ObjectName": {
                "value": "SF6 icon throwescape",
                "source": "mediawiki-metadata"
              }
            },
            "mime": "image/png"
          }
        ]
      },
      {
        "pageid": 68798,
        "ns": 6,
        "title": "File:SF6 icon lock.png",
        "imagerepository": "local",
        "imageinfo": [
          {
            "timestamp": "2023-01-20T03:22:20Z",
            "user": "Spabobin",
            "size": 19898,
            "width": 660,
            "height": 40,
            "comment": "",
            "url": "https://wiki.supercombo.gg/images/7/72/SF6_icon_lock.png",
            "descriptionurl": "https://wiki.supercombo.gg/w/File:SF6_icon_lock.png",
            "descriptionshorturl": "https://wiki.supercombo.gg/index.php?curid=68798",
            "sha1": "6b132e9cedd0f0e87ea0ca3b449614a0e4d67bbd",
            "metadata": [
              {
                "name": "frameCount",
                "value": 0
              },
              {
                "name": "loopCount",
                "value": 1
              },
              {
                "name": "duration",
                "value": 0
              },
              {
                "name": "bitDepth",
                "value": 8
              },
              {
                "name": "colorType",
                "value": "truecolour-alpha"
              },
              {
                "name": "metadata",
                "value": [
                  {
                    "name": "XResolution",
                    "value": "3779/100"
                  },
                  {
                    "name": "YResolution",
                    "value": "3779/100"
                  },
                  {
                    "name": "ResolutionUnit",
                    "value": 3
                  },
                  {
                    "name": "_MW_PNG_VERSION",
                    "value": 1
                  }
                ]
              }
            ],
            "commonmetadata": [
              {
                "name": "XResolution",
                "value": "3779/100"
              },
              {
                "name": "YResolution",
                "value": "3779/100"
              },
              {
                "name": "ResolutionUnit",
                "value": 3
              }
            ],
            "extmetadata": {
              "DateTime": {
                "value": "2023-01-20T03:22:20Z",
                "source": "mediawiki-metadata",
                "hidden": ""
              },
              "ObjectName": {
                "value": "SF6 icon lock",
                "source": "mediawiki-metadata"
              }
            },
            "mime": "image/png"
          }
        ]
      },
      {
        "pageid": 69373,
        "ns": 6,
        "title": "File:SF6 icon armorbreak.png",
        "imagerepository": "local",
        "imageinfo": [
          {
            "timestamp": "2023-03-02T10:56:56Z",
            "user": "Spabobin",
            "size": 29479,
            "width": 660,
            "height": 40,
            "comment": "",
            "url": "https://wiki.supercombo.gg/images/7/78/SF6_icon_armorbreak.png",
            "descriptionurl": "https://wiki.supercombo.gg/w/File:SF6_icon_armorbreak.png",
            "descriptionshorturl": "https://wiki.supercombo.gg/index.php?curid=69373",
            "sha1": "7b586411a83ad890c21655852819ebea88eb6eae",
            "metadata": [
              {
                "name": "frameCount",
                "value": 0
              },
              {
                "name": "loopCount",
                "value": 1
              },
              {
                "name": "duration",
                "value": 0
              },
              {
                "name": "bitDepth",
                "value": 8
              },
              {
                "name": "colorType",
                "value": "truecolour-alpha"
              },
              {
                "name": "metadata",
                "value": [
                  {
                    "name": "XResolution",
                    "value": "3779/100"
                  },
                  {
                    "name": "YResolution",
                    "value": "3779/100"
                  },
                  {
                    "name": "ResolutionUnit",
                    "value": 3
                  },
                  {
                    "name": "_MW_PNG_VERSION",
                    "value": 1
                  }
                ]
              }
            ],
            "commonmetadata": [
              {
                "name": "XResolution",
                "value": "3779/100"
              },
              {
                "name": "YResolution",
                "value": "3779/100"
              },
              {
                "name": "ResolutionUnit",
                "value": 3
              }
            ],
            "extmetadata": {
              "DateTime": {
                "value": "2023-03-02T10:56:56Z",
                "source": "mediawiki-metadata",
                "hidden": ""
              },
              "ObjectName": {
                "value": "SF6 icon armorbreak",
                "source": "mediawiki-metadata"
              }
            },
            "mime": "image/png"
          }
        ]
      },
      {
        "pageid": 80712,
        "ns": 6,
        "title": "File:SF6 Health Bars SA3 Scaling.png",
        "imagerepository": "local",
        "imageinfo": [
          {
            "timestamp": "2024-08-14T04:33:36Z",
            "user": "Spabobin",
            "size": 1948178,
            "width": 1397,
            "height": 793,
            "comment": "",
            "url": "https://wiki.supercombo.gg/images/c/c7/SF6_Health_Bars_SA3_Scaling.png",
            "descriptionurl": "https://wiki.supercombo.gg/w/File:SF6_Health_Bars_SA3_Scaling.png",
            "descriptionshorturl": "https://wiki.supercombo.gg/index.php?curid=80712",
            "sha1": "f1c37c4bfbd5b954e52d86ebe8537a9acee14a46",
            "metadata": [
              {
                "name": "frameCount",
                "value": 0
              },
              {
                "name": "loopCount",
                "value": 1
              },
              {
                "name": "duration",
                "value": 0
              },
              {
                "name": "bitDepth",
                "value": 8
              },
              {
                "name": "colorType",
                "value": "truecolour-alpha"
              },
              {
                "name": "metadata",
                "value": [
                  {
                    "name": "XResolution",
                    "value": "3779/100"
                  },
                  {
                    "name": "YResolution",
                    "value": "3779/100"
                  },
                  {
                    "name": "ResolutionUnit",
                    "value": 3
                  },
                  {
                    "name": "_MW_PNG_VERSION",
                    "value": 1
                  }
                ]
              }
            ],
            "commonmetadata": [
              {
                "name": "XResolution",
                "value": "3779/100"
              },
              {
                "name": "YResolution",
                "value": "3779/100"
              },
              {
                "name": "ResolutionUnit",
                "value": 3
              }
            ],
            "extmetadata": {
              "DateTime": {
                "value": "2024-08-14T04:33:36Z",
                "source": "mediawiki-metadata",
                "hidden": ""
              },
              "ObjectName": {
                "value": "SF6 Health Bars SA3 Scaling",
                "source": "mediawiki-metadata"
              }
            },
            "mime": "image/png"
          }
        ]
      },
      {
        "pageid": 90530,
        "ns": 6,
        "title": "File:SF6 icon forcedknockdown.png",
        "imagerepository": "local",
        "imageinfo": [
          {
            "timestamp": "2026-01-03T11:16:14Z",
            "user": "Spabobin",
            "size": 22172,
            "width": 390,
            "height": 40,
            "comment": "",
            "url": "https://wiki.supercombo.gg/images/e/e5/SF6_icon_forcedknockdown.png",
            "descriptionurl": "https://wiki.supercombo.gg/w/File:SF6_icon_forcedknockdown.png",
            "descriptionshorturl": "https://wiki.supercombo.gg/index.php?curid=90530",
            "sha1": "3ede1909077b6ac372ae981285578b71a1174210",
            "metadata": [
              {
                "name": "frameCount",
                "value": 0
              },
              {
                "name": "loopCount",
                "value": 1
              },
              {
                "name": "duration",
                "value": 0
              },
              {
                "name": "bitDepth",
                "value": 8
              },
              {
                "name": "colorType",
                "value": "truecolour-alpha"
              },
              {
                "name": "metadata",
                "value": [
                  {
                    "name": "XResolution",
                    "value": "3779/100"
                  },
                  {
                    "name": "YResolution",
                    "value": "3779/100"
                  },
                  {
                    "name": "ResolutionUnit",
                    "value": 3
                  },
                  {
                    "name": "_MW_PNG_VERSION",
                    "value": 1
                  }
                ]
              }
            ],
            "commonmetadata": [
              {
                "name": "XResolution",
                "value": "3779/100"
              },
              {
                "name": "YResolution",
                "value": "3779/100"
              },
              {
                "name": "ResolutionUnit",
                "value": 3
              }
            ],
            "extmetadata": {
              "DateTime": {
                "value": "2026-01-03T11:16:14Z",
                "source": "mediawiki-metadata",
                "hidden": ""
              },
              "ObjectName": {
                "value": "SF6 icon forcedknockdown",
                "source": "mediawiki-metadata"
              }
            },
            "mime": "image/png"
          }
        ]
      }
    ]
  }
}