{
  "batchcomplete": true,
  "query": {
    "pages": [
      {
        "pageid": 67946,
        "ns": 0,
        "title": "Street Fighter 6/Manon/Data",
        "contentmodel": "wikitext",
        "pagelanguage": "en",
        "pagelanguagehtmlcode": "en",
        "pagelanguagedir": "ltr",
        "touched": "2026-06-01T07:48:33Z",
        "lastrevid": 365228,
        "length": 71101,
        "revisions": [
          {
            "revid": 365228,
            "parentid": 365216,
            "user": "Spabobin",
            "timestamp": "2026-06-01T07:48:33Z",
            "size": 71101,
            "comment": "/* 6HPHK */"
          }
        ]
      },
      {
        "pageid": 68386,
        "ns": 0,
        "title": "Street Fighter 6/Manon/Frame data",
        "contentmodel": "wikitext",
        "pagelanguage": "en",
        "pagelanguagehtmlcode": "en",
        "pagelanguagedir": "ltr",
        "touched": "2026-06-01T07:48:35Z",
        "lastrevid": 310364,
        "length": 10765,
        "revisions": [
          {
            "revid": 310364,
            "parentid": 308190,
            "user": "Spabobin",
            "timestamp": "2024-10-19T05:09:57Z",
            "size": 10765,
            "comment": ""
          }
        ]
      }
    ]
  }
}