[
  {
    "character_slug": "kimberly",
    "move_id": "kimberly_001_5_lp",
    "punishable_threshold": 2,
    "is_safe_on_block": true,
    "is_plus_on_hit": true,
    "is_plus_on_block": false,
    "meaty_hit_adv_max": 6,
    "meaty_block_adv_max": -1,
    "startup_bucket": "5_to_7",
    "simple_punish_adv": 2,
    "derivation_notes": [
      "derived from official_raw only",
      "ignores spacing/pushback",
      "ignores character-specific punish options",
      "ignores invuln/armor/special exceptions",
      "4F baseline",
      "derivation_rule_version=1.0.0"
    ]
  },
  {
    "character_slug": "kimberly",
    "move_id": "kimberly_002_5_lk",
    "punishable_threshold": 3,
    "is_safe_on_block": true,
    "is_plus_on_hit": true,
    "is_plus_on_block": false,
    "meaty_hit_adv_max": 3,
    "meaty_block_adv_max": -1,
    "startup_bucket": "5_to_7",
    "simple_punish_adv": 3,
    "derivation_notes": [
      "derived from official_raw only",
      "ignores spacing/pushback",
      "ignores character-specific punish options",
      "ignores invuln/armor/special exceptions",
      "4F baseline",
      "derivation_rule_version=1.0.0"
    ]
  },
  {
    "character_slug": "kimberly",
    "move_id": "kimberly_003_5_mp",
    "punishable_threshold": 2,
    "is_safe_on_block": true,
    "is_plus_on_hit": true,
    "is_plus_on_block": false,
    "meaty_hit_adv_max": 5,
    "meaty_block_adv_max": 0,
    "startup_bucket": "5_to_7",
    "simple_punish_adv": 2,
    "derivation_notes": [
      "derived from official_raw only",
      "ignores spacing/pushback",
      "ignores character-specific punish options",
      "ignores invuln/armor/special exceptions",
      "4F baseline",
      "derivation_rule_version=1.0.0"
    ]
  },
  {
    "character_slug": "kimberly",
    "move_id": "kimberly_004_5_mk",
    "punishable_threshold": 4,
    "is_safe_on_block": true,
    "is_plus_on_hit": true,
    "is_plus_on_block": false,
    "meaty_hit_adv_max": 3,
    "meaty_block_adv_max": -2,
    "startup_bucket": "8_to_10",
    "simple_punish_adv": 4,
    "derivation_notes": [
      "derived from official_raw only",
      "ignores spacing/pushback",
      "ignores character-specific punish options",
      "ignores invuln/armor/special exceptions",
      "4F baseline",
      "derivation_rule_version=1.0.0"
    ]
  },
  {
    "character_slug": "kimberly",
    "move_id": "kimberly_005_5_hp",
    "punishable_threshold": 4,
    "is_safe_on_block": true,
    "is_plus_on_hit": true,
    "is_plus_on_block": false,
    "meaty_hit_adv_max": 5,
    "meaty_block_adv_max": -2,
    "startup_bucket": "8_to_10",
    "simple_punish_adv": 4,
    "derivation_notes": [
      "derived from official_raw only",
      "ignores spacing/pushback",
      "ignores character-specific punish options",
      "ignores invuln/armor/special exceptions",
      "4F baseline",
      "derivation_rule_version=1.0.0"
    ]
  },
  {
    "character_slug": "kimberly",
    "move_id": "kimberly_006_5_hk",
    "punishable_threshold": 0,
    "is_safe_on_block": true,
    "is_plus_on_hit": true,
    "is_plus_on_block": true,
    "meaty_hit_adv_max": 10,
    "meaty_block_adv_max": 5,
    "startup_bucket": "11_plus",
    "simple_punish_adv": 0,
    "derivation_notes": [
      "derived from official_raw only",
      "ignores spacing/pushback",
      "ignores character-specific punish options",
      "ignores invuln/armor/special exceptions",
      "4F baseline",
      "derivation_rule_version=1.0.0"
    ]
  },
  {
    "character_slug": "kimberly",
    "move_id": "kimberly_007_2_lp",
    "punishable_threshold": 1,
    "is_safe_on_block": true,
    "is_plus_on_hit": true,
    "is_plus_on_block": false,
    "meaty_hit_adv_max": 6,
    "meaty_block_adv_max": 1,
    "startup_bucket": "4f_or_faster",
    "simple_punish_adv": 1,
    "derivation_notes": [
      "derived from official_raw only",
      "ignores spacing/pushback",
      "ignores character-specific punish options",
      "ignores invuln/armor/special exceptions",
      "4F baseline",
      "derivation_rule_version=1.0.0"
    ]
  },
  {
    "character_slug": "kimberly",
    "move_id": "kimberly_008_2_lk",
    "punishable_threshold": 2,
    "is_safe_on_block": true,
    "is_plus_on_hit": true,
    "is_plus_on_block": false,
    "meaty_hit_adv_max": 6,
    "meaty_block_adv_max": 0,
    "startup_bucket": "5_to_7",
    "simple_punish_adv": 2,
    "derivation_notes": [
      "derived from official_raw only",
      "ignores spacing/pushback",
      "ignores character-specific punish options",
      "ignores invuln/armor/special exceptions",
      "4F baseline",
      "derivation_rule_version=1.0.0"
    ]
  },
  {
    "character_slug": "kimberly",
    "move_id": "kimberly_009_2_mp",
    "punishable_threshold": 1,
    "is_safe_on_block": true,
    "is_plus_on_hit": true,
    "is_plus_on_block": false,
    "meaty_hit_adv_max": 9,
    "meaty_block_adv_max": 1,
    "startup_bucket": "5_to_7",
    "simple_punish_adv": 1,
    "derivation_notes": [
      "derived from official_raw only",
      "ignores spacing/pushback",
      "ignores character-specific punish options",
      "ignores invuln/armor/special exceptions",
      "4F baseline",
      "derivation_rule_version=1.0.0"
    ]
  },
  {
    "character_slug": "kimberly",
    "move_id": "kimberly_010_2_mk",
    "punishable_threshold": 0,
    "is_safe_on_block": true,
    "is_plus_on_hit": true,
    "is_plus_on_block": true,
    "meaty_hit_adv_max": 7,
    "meaty_block_adv_max": 3,
    "startup_bucket": "5_to_7",
    "simple_punish_adv": 0,
    "derivation_notes": [
      "derived from official_raw only",
      "ignores spacing/pushback",
      "ignores character-specific punish options",
      "ignores invuln/armor/special exceptions",
      "4F baseline",
      "derivation_rule_version=1.0.0"
    ]
  },
  {
    "character_slug": "kimberly",
    "move_id": "kimberly_011_2_hp",
    "punishable_threshold": 2,
    "is_safe_on_block": true,
    "is_plus_on_hit": true,
    "is_plus_on_block": false,
    "meaty_hit_adv_max": 8,
    "meaty_block_adv_max": 3,
    "startup_bucket": "8_to_10",
    "simple_punish_adv": 2,
    "derivation_notes": [
      "derived from official_raw only",
      "ignores spacing/pushback",
      "ignores character-specific punish options",
      "ignores invuln/armor/special exceptions",
      "4F baseline",
      "derivation_rule_version=1.0.0"
    ]
  },
  {
    "character_slug": "kimberly",
    "move_id": "kimberly_012_2_hk",
    "punishable_threshold": 10,
    "is_safe_on_block": false,
    "is_plus_on_hit": null,
    "is_plus_on_block": false,
    "meaty_hit_adv_max": null,
    "meaty_block_adv_max": -8,
    "startup_bucket": "8_to_10",
    "simple_punish_adv": 10,
    "derivation_notes": [
      "derived from official_raw only",
      "ignores spacing/pushback",
      "ignores character-specific punish options",
      "ignores invuln/armor/special exceptions",
      "4F baseline",
      "derivation_rule_version=1.0.0"
    ]
  },
  {
    "character_slug": "kimberly",
    "move_id": "kimberly_013_j_lp",
    "punishable_threshold": null,
    "is_safe_on_block": null,
    "is_plus_on_hit": null,
    "is_plus_on_block": null,
    "meaty_hit_adv_max": null,
    "meaty_block_adv_max": null,
    "startup_bucket": "4f_or_faster",
    "simple_punish_adv": null,
    "derivation_notes": [
      "derived from official_raw only",
      "ignores spacing/pushback",
      "ignores character-specific punish options",
      "ignores invuln/armor/special exceptions",
      "4F baseline",
      "derivation_rule_version=1.0.0"
    ]
  },
  {
    "character_slug": "kimberly",
    "move_id": "kimberly_014_j_lk",
    "punishable_threshold": null,
    "is_safe_on_block": null,
    "is_plus_on_hit": null,
    "is_plus_on_block": null,
    "meaty_hit_adv_max": null,
    "meaty_block_adv_max": null,
    "startup_bucket": "5_to_7",
    "simple_punish_adv": null,
    "derivation_notes": [
      "derived from official_raw only",
      "ignores spacing/pushback",
      "ignores character-specific punish options",
      "ignores invuln/armor/special exceptions",
      "4F baseline",
      "derivation_rule_version=1.0.0"
    ]
  },
  {
    "character_slug": "kimberly",
    "move_id": "kimberly_015_j_mp",
    "punishable_threshold": null,
    "is_safe_on_block": null,
    "is_plus_on_hit": null,
    "is_plus_on_block": null,
    "meaty_hit_adv_max": null,
    "meaty_block_adv_max": null,
    "startup_bucket": "5_to_7",
    "simple_punish_adv": null,
    "derivation_notes": [
      "derived from official_raw only",
      "ignores spacing/pushback",
      "ignores character-specific punish options",
      "ignores invuln/armor/special exceptions",
      "4F baseline",
      "derivation_rule_version=1.0.0"
    ]
  },
  {
    "character_slug": "kimberly",
    "move_id": "kimberly_016_j_mk",
    "punishable_threshold": null,
    "is_safe_on_block": null,
    "is_plus_on_hit": null,
    "is_plus_on_block": null,
    "meaty_hit_adv_max": null,
    "meaty_block_adv_max": null,
    "startup_bucket": "5_to_7",
    "simple_punish_adv": null,
    "derivation_notes": [
      "derived from official_raw only",
      "ignores spacing/pushback",
      "ignores character-specific punish options",
      "ignores invuln/armor/special exceptions",
      "4F baseline",
      "derivation_rule_version=1.0.0"
    ]
  },
  {
    "character_slug": "kimberly",
    "move_id": "kimberly_017_j_hp",
    "punishable_threshold": null,
    "is_safe_on_block": null,
    "is_plus_on_hit": null,
    "is_plus_on_block": null,
    "meaty_hit_adv_max": null,
    "meaty_block_adv_max": null,
    "startup_bucket": "8_to_10",
    "simple_punish_adv": null,
    "derivation_notes": [
      "derived from official_raw only",
      "ignores spacing/pushback",
      "ignores character-specific punish options",
      "ignores invuln/armor/special exceptions",
      "4F baseline",
      "derivation_rule_version=1.0.0"
    ]
  },
  {
    "character_slug": "kimberly",
    "move_id": "kimberly_018_j_hk",
    "punishable_threshold": null,
    "is_safe_on_block": null,
    "is_plus_on_hit": null,
    "is_plus_on_block": null,
    "meaty_hit_adv_max": null,
    "meaty_block_adv_max": null,
    "startup_bucket": "8_to_10",
    "simple_punish_adv": null,
    "derivation_notes": [
      "derived from official_raw only",
      "ignores spacing/pushback",
      "ignores character-specific punish options",
      "ignores invuln/armor/special exceptions",
      "4F baseline",
      "derivation_rule_version=1.0.0"
    ]
  },
  {
    "character_slug": "kimberly",
    "move_id": "kimberly_019_3_mk",
    "punishable_threshold": 5,
    "is_safe_on_block": false,
    "is_plus_on_hit": true,
    "is_plus_on_block": false,
    "meaty_hit_adv_max": 10,
    "meaty_block_adv_max": 4,
    "startup_bucket": "11_plus",
    "simple_punish_adv": 5,
    "derivation_notes": [
      "derived from official_raw only",
      "ignores spacing/pushback",
      "ignores character-specific punish options",
      "ignores invuln/armor/special exceptions",
      "4F baseline",
      "derivation_rule_version=1.0.0"
    ]
  },
  {
    "character_slug": "kimberly",
    "move_id": "kimberly_020_4_hk",
    "punishable_threshold": 3,
    "is_safe_on_block": true,
    "is_plus_on_hit": true,
    "is_plus_on_block": false,
    "meaty_hit_adv_max": 5,
    "meaty_block_adv_max": -2,
    "startup_bucket": "11_plus",
    "simple_punish_adv": 3,
    "derivation_notes": [
      "derived from official_raw only",
      "ignores spacing/pushback",
      "ignores character-specific punish options",
      "ignores invuln/armor/special exceptions",
      "4F baseline",
      "derivation_rule_version=1.0.0"
    ]
  },
  {
    "character_slug": "kimberly",
    "move_id": "kimberly_021_6_hk",
    "punishable_threshold": 3,
    "is_safe_on_block": true,
    "is_plus_on_hit": true,
    "is_plus_on_block": false,
    "meaty_hit_adv_max": 3,
    "meaty_block_adv_max": -1,
    "startup_bucket": "11_plus",
    "simple_punish_adv": 3,
    "derivation_notes": [
      "derived from official_raw only",
      "ignores spacing/pushback",
      "ignores character-specific punish options",
      "ignores invuln/armor/special exceptions",
      "4F baseline",
      "derivation_rule_version=1.0.0"
    ]
  },
  {
    "character_slug": "kimberly",
    "move_id": "kimberly_022_7_8_9",
    "punishable_threshold": 22,
    "is_safe_on_block": false,
    "is_plus_on_hit": false,
    "is_plus_on_block": false,
    "meaty_hit_adv_max": null,
    "meaty_block_adv_max": null,
    "startup_bucket": null,
    "simple_punish_adv": 22,
    "derivation_notes": [
      "derived from official_raw only",
      "ignores spacing/pushback",
      "ignores character-specific punish options",
      "ignores invuln/armor/special exceptions",
      "4F baseline",
      "derivation_rule_version=1.0.0"
    ]
  },
  {
    "character_slug": "kimberly",
    "move_id": "kimberly_023_2_mp",
    "punishable_threshold": null,
    "is_safe_on_block": null,
    "is_plus_on_hit": null,
    "is_plus_on_block": null,
    "meaty_hit_adv_max": null,
    "meaty_block_adv_max": null,
    "startup_bucket": "11_plus",
    "simple_punish_adv": null,
    "derivation_notes": [
      "derived from official_raw only",
      "ignores spacing/pushback",
      "ignores character-specific punish options",
      "ignores invuln/armor/special exceptions",
      "4F baseline",
      "derivation_rule_version=1.0.0"
    ]
  },
  {
    "character_slug": "kimberly",
    "move_id": "kimberly_024_mp_hp",
    "punishable_threshold": 12,
    "is_safe_on_block": false,
    "is_plus_on_hit": null,
    "is_plus_on_block": false,
    "meaty_hit_adv_max": null,
    "meaty_block_adv_max": -10,
    "startup_bucket": "8_to_10",
    "simple_punish_adv": 12,
    "derivation_notes": [
      "derived from official_raw only",
      "ignores spacing/pushback",
      "ignores character-specific punish options",
      "ignores invuln/armor/special exceptions",
      "4F baseline",
      "derivation_rule_version=1.0.0"
    ]
  },
  {
    "character_slug": "kimberly",
    "move_id": "kimberly_025_lp_mp",
    "punishable_threshold": 6,
    "is_safe_on_block": false,
    "is_plus_on_hit": true,
    "is_plus_on_block": false,
    "meaty_hit_adv_max": 3,
    "meaty_block_adv_max": -4,
    "startup_bucket": "5_to_7",
    "simple_punish_adv": 6,
    "derivation_notes": [
      "derived from official_raw only",
      "ignores spacing/pushback",
      "ignores character-specific punish options",
      "ignores invuln/armor/special exceptions",
      "4F baseline",
      "derivation_rule_version=1.0.0"
    ]
  },
  {
    "character_slug": "kimberly",
    "move_id": "kimberly_026_lp_mp_hp",
    "punishable_threshold": 10,
    "is_safe_on_block": false,
    "is_plus_on_hit": null,
    "is_plus_on_block": false,
    "meaty_hit_adv_max": null,
    "meaty_block_adv_max": -9,
    "startup_bucket": "11_plus",
    "simple_punish_adv": 10,
    "derivation_notes": [
      "derived from official_raw only",
      "ignores spacing/pushback",
      "ignores character-specific punish options",
      "ignores invuln/armor/special exceptions",
      "4F baseline",
      "derivation_rule_version=1.0.0"
    ]
  },
  {
    "character_slug": "kimberly",
    "move_id": "kimberly_027_lp_mp_hp_hk",
    "punishable_threshold": 12,
    "is_safe_on_block": false,
    "is_plus_on_hit": null,
    "is_plus_on_block": false,
    "meaty_hit_adv_max": null,
    "meaty_block_adv_max": -10,
    "startup_bucket": "11_plus",
    "simple_punish_adv": 12,
    "derivation_notes": [
      "derived from official_raw only",
      "ignores spacing/pushback",
      "ignores character-specific punish options",
      "ignores invuln/armor/special exceptions",
      "4F baseline",
      "derivation_rule_version=1.0.0"
    ]
  },
  {
    "character_slug": "kimberly",
    "move_id": "kimberly_028_lp_mp_2_hp",
    "punishable_threshold": 10,
    "is_safe_on_block": false,
    "is_plus_on_hit": true,
    "is_plus_on_block": false,
    "meaty_hit_adv_max": 3,
    "meaty_block_adv_max": -9,
    "startup_bucket": "8_to_10",
    "simple_punish_adv": 10,
    "derivation_notes": [
      "derived from official_raw only",
      "ignores spacing/pushback",
      "ignores character-specific punish options",
      "ignores invuln/armor/special exceptions",
      "4F baseline",
      "derivation_rule_version=1.0.0"
    ]
  },
  {
    "character_slug": "kimberly",
    "move_id": "kimberly_029_lp_mp_2_hp_hk",
    "punishable_threshold": 12,
    "is_safe_on_block": false,
    "is_plus_on_hit": null,
    "is_plus_on_block": false,
    "meaty_hit_adv_max": null,
    "meaty_block_adv_max": -10,
    "startup_bucket": "11_plus",
    "simple_punish_adv": 12,
    "derivation_notes": [
      "derived from official_raw only",
      "ignores spacing/pushback",
      "ignores character-specific punish options",
      "ignores invuln/armor/special exceptions",
      "4F baseline",
      "derivation_rule_version=1.0.0"
    ]
  },
  {
    "character_slug": "kimberly",
    "move_id": "kimberly_030_lp_mp_2_hp_2_hk",
    "punishable_threshold": 12,
    "is_safe_on_block": false,
    "is_plus_on_hit": null,
    "is_plus_on_block": false,
    "meaty_hit_adv_max": null,
    "meaty_block_adv_max": -10,
    "startup_bucket": "11_plus",
    "simple_punish_adv": 12,
    "derivation_notes": [
      "derived from official_raw only",
      "ignores spacing/pushback",
      "ignores character-specific punish options",
      "ignores invuln/armor/special exceptions",
      "4F baseline",
      "derivation_rule_version=1.0.0"
    ]
  },
  {
    "character_slug": "kimberly",
    "move_id": "kimberly_037_2_3_6_k",
    "punishable_threshold": null,
    "is_safe_on_block": null,
    "is_plus_on_hit": null,
    "is_plus_on_block": null,
    "meaty_hit_adv_max": null,
    "meaty_block_adv_max": null,
    "startup_bucket": null,
    "simple_punish_adv": null,
    "derivation_notes": [
      "derived from official_raw only",
      "ignores spacing/pushback",
      "ignores character-specific punish options",
      "ignores invuln/armor/special exceptions",
      "4F baseline",
      "derivation_rule_version=1.0.0"
    ]
  },
  {
    "character_slug": "kimberly",
    "move_id": "kimberly_038_2_3_6_k_k",
    "punishable_threshold": null,
    "is_safe_on_block": null,
    "is_plus_on_hit": null,
    "is_plus_on_block": null,
    "meaty_hit_adv_max": null,
    "meaty_block_adv_max": null,
    "startup_bucket": null,
    "simple_punish_adv": null,
    "derivation_notes": [
      "derived from official_raw only",
      "ignores spacing/pushback",
      "ignores character-specific punish options",
      "ignores invuln/armor/special exceptions",
      "4F baseline",
      "derivation_rule_version=1.0.0"
    ]
  },
  {
    "character_slug": "kimberly",
    "move_id": "kimberly_039_p",
    "punishable_threshold": null,
    "is_safe_on_block": null,
    "is_plus_on_hit": null,
    "is_plus_on_block": null,
    "meaty_hit_adv_max": null,
    "meaty_block_adv_max": null,
    "startup_bucket": null,
    "simple_punish_adv": null,
    "derivation_notes": [
      "derived from official_raw only",
      "ignores spacing/pushback",
      "ignores character-specific punish options",
      "ignores invuln/armor/special exceptions",
      "4F baseline",
      "derivation_rule_version=1.0.0"
    ]
  },
  {
    "character_slug": "kimberly",
    "move_id": "kimberly_040_p",
    "punishable_threshold": null,
    "is_safe_on_block": null,
    "is_plus_on_hit": null,
    "is_plus_on_block": null,
    "meaty_hit_adv_max": null,
    "meaty_block_adv_max": null,
    "startup_bucket": null,
    "simple_punish_adv": null,
    "derivation_notes": [
      "derived from official_raw only",
      "ignores spacing/pushback",
      "ignores character-specific punish options",
      "ignores invuln/armor/special exceptions",
      "4F baseline",
      "derivation_rule_version=1.0.0"
    ]
  },
  {
    "character_slug": "kimberly",
    "move_id": "kimberly_041_lk",
    "punishable_threshold": 0,
    "is_safe_on_block": true,
    "is_plus_on_hit": null,
    "is_plus_on_block": true,
    "meaty_hit_adv_max": null,
    "meaty_block_adv_max": 7,
    "startup_bucket": "11_plus",
    "simple_punish_adv": 0,
    "derivation_notes": [
      "derived from official_raw only",
      "ignores spacing/pushback",
      "ignores character-specific punish options",
      "ignores invuln/armor/special exceptions",
      "4F baseline",
      "derivation_rule_version=1.0.0"
    ]
  },
  {
    "character_slug": "kimberly",
    "move_id": "kimberly_043_mk",
    "punishable_threshold": 12,
    "is_safe_on_block": false,
    "is_plus_on_hit": null,
    "is_plus_on_block": false,
    "meaty_hit_adv_max": null,
    "meaty_block_adv_max": -1,
    "startup_bucket": "8_to_10",
    "simple_punish_adv": 12,
    "derivation_notes": [
      "derived from official_raw only",
      "ignores spacing/pushback",
      "ignores character-specific punish options",
      "ignores invuln/armor/special exceptions",
      "4F baseline",
      "derivation_rule_version=1.0.0"
    ]
  },
  {
    "character_slug": "kimberly",
    "move_id": "kimberly_045_hk",
    "punishable_threshold": 3,
    "is_safe_on_block": true,
    "is_plus_on_hit": null,
    "is_plus_on_block": false,
    "meaty_hit_adv_max": null,
    "meaty_block_adv_max": 1,
    "startup_bucket": "11_plus",
    "simple_punish_adv": 3,
    "derivation_notes": [
      "derived from official_raw only",
      "ignores spacing/pushback",
      "ignores character-specific punish options",
      "ignores invuln/armor/special exceptions",
      "4F baseline",
      "derivation_rule_version=1.0.0"
    ]
  },
  {
    "character_slug": "kimberly",
    "move_id": "kimberly_049_p",
    "punishable_threshold": null,
    "is_safe_on_block": null,
    "is_plus_on_hit": null,
    "is_plus_on_block": null,
    "meaty_hit_adv_max": null,
    "meaty_block_adv_max": null,
    "startup_bucket": "11_plus",
    "simple_punish_adv": null,
    "derivation_notes": [
      "derived from official_raw only",
      "ignores spacing/pushback",
      "ignores character-specific punish options",
      "ignores invuln/armor/special exceptions",
      "4F baseline",
      "derivation_rule_version=1.0.0"
    ]
  },
  {
    "character_slug": "kimberly",
    "move_id": "kimberly_050_p",
    "punishable_threshold": null,
    "is_safe_on_block": null,
    "is_plus_on_hit": null,
    "is_plus_on_block": null,
    "meaty_hit_adv_max": null,
    "meaty_block_adv_max": null,
    "startup_bucket": "11_plus",
    "simple_punish_adv": null,
    "derivation_notes": [
      "derived from official_raw only",
      "ignores spacing/pushback",
      "ignores character-specific punish options",
      "ignores invuln/armor/special exceptions",
      "4F baseline",
      "derivation_rule_version=1.0.0"
    ]
  },
  {
    "character_slug": "kimberly",
    "move_id": "kimberly_051_k",
    "punishable_threshold": 8,
    "is_safe_on_block": false,
    "is_plus_on_hit": null,
    "is_plus_on_block": false,
    "meaty_hit_adv_max": null,
    "meaty_block_adv_max": -3,
    "startup_bucket": "11_plus",
    "simple_punish_adv": 8,
    "derivation_notes": [
      "derived from official_raw only",
      "ignores spacing/pushback",
      "ignores character-specific punish options",
      "ignores invuln/armor/special exceptions",
      "4F baseline",
      "derivation_rule_version=1.0.0"
    ]
  },
  {
    "character_slug": "kimberly",
    "move_id": "kimberly_052_k",
    "punishable_threshold": 8,
    "is_safe_on_block": false,
    "is_plus_on_hit": null,
    "is_plus_on_block": false,
    "meaty_hit_adv_max": null,
    "meaty_block_adv_max": -3,
    "startup_bucket": "11_plus",
    "simple_punish_adv": 8,
    "derivation_notes": [
      "derived from official_raw only",
      "ignores spacing/pushback",
      "ignores character-specific punish options",
      "ignores invuln/armor/special exceptions",
      "4F baseline",
      "derivation_rule_version=1.0.0"
    ]
  },
  {
    "character_slug": "kimberly",
    "move_id": "kimberly_053_2_3_6_lp",
    "punishable_threshold": 4,
    "is_safe_on_block": true,
    "is_plus_on_hit": true,
    "is_plus_on_block": false,
    "meaty_hit_adv_max": 5,
    "meaty_block_adv_max": -2,
    "startup_bucket": "8_to_10",
    "simple_punish_adv": 4,
    "derivation_notes": [
      "derived from official_raw only",
      "ignores spacing/pushback",
      "ignores character-specific punish options",
      "ignores invuln/armor/special exceptions",
      "4F baseline",
      "derivation_rule_version=1.0.0"
    ]
  },
  {
    "character_slug": "kimberly",
    "move_id": "kimberly_057_2_1_4_p",
    "punishable_threshold": null,
    "is_safe_on_block": null,
    "is_plus_on_hit": null,
    "is_plus_on_block": null,
    "meaty_hit_adv_max": null,
    "meaty_block_adv_max": null,
    "startup_bucket": null,
    "simple_punish_adv": null,
    "derivation_notes": [
      "derived from official_raw only",
      "ignores spacing/pushback",
      "ignores character-specific punish options",
      "ignores invuln/armor/special exceptions",
      "4F baseline",
      "derivation_rule_version=1.0.0"
    ]
  },
  {
    "character_slug": "kimberly",
    "move_id": "kimberly_058_2_1_4_p_p",
    "punishable_threshold": null,
    "is_safe_on_block": null,
    "is_plus_on_hit": null,
    "is_plus_on_block": null,
    "meaty_hit_adv_max": null,
    "meaty_block_adv_max": null,
    "startup_bucket": null,
    "simple_punish_adv": null,
    "derivation_notes": [
      "derived from official_raw only",
      "ignores spacing/pushback",
      "ignores character-specific punish options",
      "ignores invuln/armor/special exceptions",
      "4F baseline",
      "derivation_rule_version=1.0.0"
    ]
  },
  {
    "character_slug": "kimberly",
    "move_id": "kimberly_059_2_2_p",
    "punishable_threshold": null,
    "is_safe_on_block": null,
    "is_plus_on_hit": null,
    "is_plus_on_block": null,
    "meaty_hit_adv_max": null,
    "meaty_block_adv_max": null,
    "startup_bucket": null,
    "simple_punish_adv": null,
    "derivation_notes": [
      "derived from official_raw only",
      "ignores spacing/pushback",
      "ignores character-specific punish options",
      "ignores invuln/armor/special exceptions",
      "4F baseline",
      "derivation_rule_version=1.0.0"
    ]
  },
  {
    "character_slug": "kimberly",
    "move_id": "kimberly_060_2_2_p_p",
    "punishable_threshold": null,
    "is_safe_on_block": null,
    "is_plus_on_hit": null,
    "is_plus_on_block": null,
    "meaty_hit_adv_max": null,
    "meaty_block_adv_max": null,
    "startup_bucket": null,
    "simple_punish_adv": null,
    "derivation_notes": [
      "derived from official_raw only",
      "ignores spacing/pushback",
      "ignores character-specific punish options",
      "ignores invuln/armor/special exceptions",
      "4F baseline",
      "derivation_rule_version=1.0.0"
    ]
  },
  {
    "character_slug": "kimberly",
    "move_id": "kimberly_067_2_3_6_p",
    "punishable_threshold": null,
    "is_safe_on_block": null,
    "is_plus_on_hit": null,
    "is_plus_on_block": null,
    "meaty_hit_adv_max": null,
    "meaty_block_adv_max": null,
    "startup_bucket": "5_to_7",
    "simple_punish_adv": null,
    "derivation_notes": [
      "derived from official_raw only",
      "ignores spacing/pushback",
      "ignores character-specific punish options",
      "ignores invuln/armor/special exceptions",
      "4F baseline",
      "derivation_rule_version=1.0.0"
    ]
  },
  {
    "character_slug": "kimberly",
    "move_id": "kimberly_068_2_3_6_p_p",
    "punishable_threshold": null,
    "is_safe_on_block": null,
    "is_plus_on_hit": null,
    "is_plus_on_block": null,
    "meaty_hit_adv_max": null,
    "meaty_block_adv_max": null,
    "startup_bucket": "5_to_7",
    "simple_punish_adv": null,
    "derivation_notes": [
      "derived from official_raw only",
      "ignores spacing/pushback",
      "ignores character-specific punish options",
      "ignores invuln/armor/special exceptions",
      "4F baseline",
      "derivation_rule_version=1.0.0"
    ]
  },
  {
    "character_slug": "kimberly",
    "move_id": "kimberly_069_2_3_6_2_3_6_k",
    "punishable_threshold": 25,
    "is_safe_on_block": false,
    "is_plus_on_hit": null,
    "is_plus_on_block": false,
    "meaty_hit_adv_max": null,
    "meaty_block_adv_max": -11,
    "startup_bucket": "8_to_10",
    "simple_punish_adv": 25,
    "derivation_notes": [
      "derived from official_raw only",
      "ignores spacing/pushback",
      "ignores character-specific punish options",
      "ignores invuln/armor/special exceptions",
      "4F baseline",
      "derivation_rule_version=1.0.0"
    ]
  },
  {
    "character_slug": "kimberly",
    "move_id": "kimberly_070_2_3_6_2_3_6_k",
    "punishable_threshold": 25,
    "is_safe_on_block": false,
    "is_plus_on_hit": null,
    "is_plus_on_block": false,
    "meaty_hit_adv_max": null,
    "meaty_block_adv_max": -11,
    "startup_bucket": "8_to_10",
    "simple_punish_adv": 25,
    "derivation_notes": [
      "derived from official_raw only",
      "ignores spacing/pushback",
      "ignores character-specific punish options",
      "ignores invuln/armor/special exceptions",
      "4F baseline",
      "derivation_rule_version=1.0.0"
    ]
  },
  {
    "character_slug": "kimberly",
    "move_id": "kimberly_071_2_1_4_2_1_4_p",
    "punishable_threshold": 25,
    "is_safe_on_block": false,
    "is_plus_on_hit": null,
    "is_plus_on_block": false,
    "meaty_hit_adv_max": null,
    "meaty_block_adv_max": -18,
    "startup_bucket": "11_plus",
    "simple_punish_adv": 25,
    "derivation_notes": [
      "derived from official_raw only",
      "ignores spacing/pushback",
      "ignores character-specific punish options",
      "ignores invuln/armor/special exceptions",
      "4F baseline",
      "derivation_rule_version=1.0.0"
    ]
  },
  {
    "character_slug": "kimberly",
    "move_id": "kimberly_073_2_3_6_2_3_6_p",
    "punishable_threshold": 35,
    "is_safe_on_block": false,
    "is_plus_on_hit": null,
    "is_plus_on_block": false,
    "meaty_hit_adv_max": null,
    "meaty_block_adv_max": -30,
    "startup_bucket": "8_to_10",
    "simple_punish_adv": 35,
    "derivation_notes": [
      "derived from official_raw only",
      "ignores spacing/pushback",
      "ignores character-specific punish options",
      "ignores invuln/armor/special exceptions",
      "4F baseline",
      "derivation_rule_version=1.0.0"
    ]
  },
  {
    "character_slug": "kimberly",
    "move_id": "kimberly_074_2_3_6_2_3_6_p",
    "punishable_threshold": 35,
    "is_safe_on_block": false,
    "is_plus_on_hit": null,
    "is_plus_on_block": false,
    "meaty_hit_adv_max": null,
    "meaty_block_adv_max": -30,
    "startup_bucket": "8_to_10",
    "simple_punish_adv": 35,
    "derivation_notes": [
      "derived from official_raw only",
      "ignores spacing/pushback",
      "ignores character-specific punish options",
      "ignores invuln/armor/special exceptions",
      "4F baseline",
      "derivation_rule_version=1.0.0"
    ]
  },
  {
    "character_slug": "kimberly",
    "move_id": "kimberly_075_5_6_lplk",
    "punishable_threshold": null,
    "is_safe_on_block": null,
    "is_plus_on_hit": null,
    "is_plus_on_block": null,
    "meaty_hit_adv_max": null,
    "meaty_block_adv_max": null,
    "startup_bucket": "5_to_7",
    "simple_punish_adv": null,
    "derivation_notes": [
      "derived from official_raw only",
      "ignores spacing/pushback",
      "ignores character-specific punish options",
      "ignores invuln/armor/special exceptions",
      "4F baseline",
      "derivation_rule_version=1.0.0"
    ]
  },
  {
    "character_slug": "kimberly",
    "move_id": "kimberly_076_4_lplk",
    "punishable_threshold": null,
    "is_safe_on_block": null,
    "is_plus_on_hit": null,
    "is_plus_on_block": null,
    "meaty_hit_adv_max": null,
    "meaty_block_adv_max": null,
    "startup_bucket": "5_to_7",
    "simple_punish_adv": null,
    "derivation_notes": [
      "derived from official_raw only",
      "ignores spacing/pushback",
      "ignores character-specific punish options",
      "ignores invuln/armor/special exceptions",
      "4F baseline",
      "derivation_rule_version=1.0.0"
    ]
  },
  {
    "character_slug": "kimberly",
    "move_id": "kimberly_077_6_6",
    "punishable_threshold": null,
    "is_safe_on_block": null,
    "is_plus_on_hit": null,
    "is_plus_on_block": null,
    "meaty_hit_adv_max": null,
    "meaty_block_adv_max": null,
    "startup_bucket": null,
    "simple_punish_adv": null,
    "derivation_notes": [
      "derived from official_raw only",
      "ignores spacing/pushback",
      "ignores character-specific punish options",
      "ignores invuln/armor/special exceptions",
      "4F baseline",
      "derivation_rule_version=1.0.0"
    ]
  },
  {
    "character_slug": "kimberly",
    "move_id": "kimberly_078_4_4",
    "punishable_threshold": null,
    "is_safe_on_block": null,
    "is_plus_on_hit": null,
    "is_plus_on_block": null,
    "meaty_hit_adv_max": null,
    "meaty_block_adv_max": null,
    "startup_bucket": null,
    "simple_punish_adv": null,
    "derivation_notes": [
      "derived from official_raw only",
      "ignores spacing/pushback",
      "ignores character-specific punish options",
      "ignores invuln/armor/special exceptions",
      "4F baseline",
      "derivation_rule_version=1.0.0"
    ]
  },
  {
    "character_slug": "kimberly",
    "move_id": "kimberly_079_hphk",
    "punishable_threshold": 3,
    "is_safe_on_block": true,
    "is_plus_on_hit": null,
    "is_plus_on_block": false,
    "meaty_hit_adv_max": null,
    "meaty_block_adv_max": -2,
    "startup_bucket": "11_plus",
    "simple_punish_adv": 3,
    "derivation_notes": [
      "derived from official_raw only",
      "ignores spacing/pushback",
      "ignores character-specific punish options",
      "ignores invuln/armor/special exceptions",
      "4F baseline",
      "derivation_rule_version=1.0.0"
    ]
  },
  {
    "character_slug": "kimberly",
    "move_id": "kimberly_080_6_hphk",
    "punishable_threshold": 6,
    "is_safe_on_block": false,
    "is_plus_on_hit": null,
    "is_plus_on_block": false,
    "meaty_hit_adv_max": null,
    "meaty_block_adv_max": -4,
    "startup_bucket": "11_plus",
    "simple_punish_adv": 6,
    "derivation_notes": [
      "derived from official_raw only",
      "ignores spacing/pushback",
      "ignores character-specific punish options",
      "ignores invuln/armor/special exceptions",
      "4F baseline",
      "derivation_rule_version=1.0.0"
    ]
  },
  {
    "character_slug": "kimberly",
    "move_id": "kimberly_081_6_hphk",
    "punishable_threshold": 6,
    "is_safe_on_block": false,
    "is_plus_on_hit": null,
    "is_plus_on_block": false,
    "meaty_hit_adv_max": null,
    "meaty_block_adv_max": -4,
    "startup_bucket": "11_plus",
    "simple_punish_adv": 6,
    "derivation_notes": [
      "derived from official_raw only",
      "ignores spacing/pushback",
      "ignores character-specific punish options",
      "ignores invuln/armor/special exceptions",
      "4F baseline",
      "derivation_rule_version=1.0.0"
    ]
  },
  {
    "character_slug": "kimberly",
    "move_id": "kimberly_083_mpmk",
    "punishable_threshold": null,
    "is_safe_on_block": null,
    "is_plus_on_hit": null,
    "is_plus_on_block": null,
    "meaty_hit_adv_max": null,
    "meaty_block_adv_max": null,
    "startup_bucket": "4f_or_faster",
    "simple_punish_adv": null,
    "derivation_notes": [
      "derived from official_raw only",
      "ignores spacing/pushback",
      "ignores character-specific punish options",
      "ignores invuln/armor/special exceptions",
      "4F baseline",
      "derivation_rule_version=1.0.0"
    ]
  },
  {
    "character_slug": "kimberly",
    "move_id": "kimberly_084_mpmk",
    "punishable_threshold": null,
    "is_safe_on_block": null,
    "is_plus_on_hit": null,
    "is_plus_on_block": null,
    "meaty_hit_adv_max": null,
    "meaty_block_adv_max": null,
    "startup_bucket": "4f_or_faster",
    "simple_punish_adv": null,
    "derivation_notes": [
      "derived from official_raw only",
      "ignores spacing/pushback",
      "ignores character-specific punish options",
      "ignores invuln/armor/special exceptions",
      "4F baseline",
      "derivation_rule_version=1.0.0"
    ]
  },
  {
    "character_slug": "kimberly",
    "move_id": "kimberly_085_6_6",
    "punishable_threshold": null,
    "is_safe_on_block": null,
    "is_plus_on_hit": null,
    "is_plus_on_block": null,
    "meaty_hit_adv_max": null,
    "meaty_block_adv_max": null,
    "startup_bucket": null,
    "simple_punish_adv": null,
    "derivation_notes": [
      "derived from official_raw only",
      "ignores spacing/pushback",
      "ignores character-specific punish options",
      "ignores invuln/armor/special exceptions",
      "4F baseline",
      "derivation_rule_version=1.0.0"
    ]
  },
  {
    "character_slug": "kimberly",
    "move_id": "kimberly_086_6_6_5_6_mpmk",
    "punishable_threshold": null,
    "is_safe_on_block": null,
    "is_plus_on_hit": null,
    "is_plus_on_block": null,
    "meaty_hit_adv_max": null,
    "meaty_block_adv_max": null,
    "startup_bucket": null,
    "simple_punish_adv": null,
    "derivation_notes": [
      "derived from official_raw only",
      "ignores spacing/pushback",
      "ignores character-specific punish options",
      "ignores invuln/armor/special exceptions",
      "4F baseline",
      "derivation_rule_version=1.0.0"
    ]
  }
]
